testcontainers/azurite/__init__.py
tests/test_azurite.py
testcontainers_azurite-0.0.1rc1.dist-info/METADATA
testcontainers_azurite-0.0.1rc1.dist-info/WHEEL
testcontainers_azurite-0.0.1rc1.dist-info/top_level.txt
testcontainers_azurite-0.0.1rc1.dist-info/RECORD
